jacobsjsonschema/__init__.py
jacobsjsonschema/_version.py
jacobsjsonschema/bool_compare_util.py
jacobsjsonschema/draft2019_09.py
jacobsjsonschema/draft2020_12.py
jacobsjsonschema/draft4.py
jacobsjsonschema/draft6.py
jacobsjsonschema/draft7.py
tests/__init__.py
tests/context.py
tests/integrated/__init__.py
tests/integrated/test_suite_4_docs.py
tests/integrated/test_suite_6_docs.py
tests/integrated/test_suite_7_docs.py
tests/standalone/__init__.py
tests/standalone/test_suite_4.py
tests/standalone/test_suite_6.py
tests/standalone/test_suite_7.py
tests/unittests/__init__.py
tests/unittests/test_invalid_schema.py
tests/unittests/test_lazy.py
tests/unittests/test_references.py
tests/unittests/test_validate.py
jacobs_json_schema-0.4.2.dist-info/LICENSE
jacobs_json_schema-0.4.2.dist-info/METADATA
jacobs_json_schema-0.4.2.dist-info/WHEEL
jacobs_json_schema-0.4.2.dist-info/top_level.txt
jacobs_json_schema-0.4.2.dist-info/RECORD
