Metadata-Version: 2.1
Name: jacobs-json-schema
Version: 0.4.2
Summary: Another JSON-Schema Validator
Home-page: https://github.com/pearmaster/jacobs-json-schema
Author: Jacob Brunson
Author-email: pypi@jacobbrunson.com
License: MIT
Keywords: json schema,validation,data validation,json
Platform: UNKNOWN
Classifier: Intended Audience :: Developers
Classifier: License :: OSI Approved :: MIT License
Classifier: Operating System :: OS Independent
Classifier: Programming Language :: Python :: 3.5
Classifier: Programming Language :: Python :: 3.6
Classifier: Programming Language :: Python :: 3.7
Classifier: Programming Language :: Python :: 3.8
Classifier: Programming Language :: Python :: 3.9
Classifier: Programming Language :: Python :: 3.10
Classifier: Programming Language :: Python :: 3.11
Requires-Python: >=3.5
